README.md
setup.cfg
setup.py
distributions_sv/Binomialdistribution.py
distributions_sv/Gaussiandistribution.py
distributions_sv/Generaldistribution.py
distributions_sv/__init__.py
distributions_sv.egg-info/PKG-INFO
distributions_sv.egg-info/SOURCES.txt
distributions_sv.egg-info/dependency_links.txt
distributions_sv.egg-info/not-zip-safe
distributions_sv.egg-info/top_level.txt