Metadata-Version: 1.0
Name: distributions-sv
Version: 0.1
Summary: Gaussian distributions
Home-page: UNKNOWN
Author: soheyl
Author-email: soheyl@gmail.com
License: UNKNOWN
Platform: UNKNOWN
